bloyid/__init__.py
bloyid/_enums.py
bloyid/attachment.py
bloyid/button.py
bloyid/buttoninteraction.py
bloyid/channel.py
bloyid/client.py
bloyid/context.py
bloyid/invite.py
bloyid/member.py
bloyid/message.py
bloyid/post.py
bloyid/roles.py
bloyid/server.py
bloyid/status.py
bloyid-0.8.dist-info/LICENSE.TXT
bloyid-0.8.dist-info/METADATA
bloyid-0.8.dist-info/WHEEL
bloyid-0.8.dist-info/top_level.txt
bloyid-0.8.dist-info/RECORD
