Metadata-Version: 2.1
Name: bloyid
Version: 0.8
License-File: LICENSE.TXT
Requires-Dist: aiohttp>=3.11.13
Requires-Dist: websockets>=15.0.1
Requires-Dist: requests>=2.32.3
